emailotp/__init__.py
emailotp/emailotp.py
emailotp-2.1.7.dist-info/LICENSE
emailotp-2.1.7.dist-info/METADATA
emailotp-2.1.7.dist-info/WHEEL
emailotp-2.1.7.dist-info/top_level.txt
emailotp-2.1.7.dist-info/RECORD
