Metadata-Version: 2.1
Name: emailotp
Version: 2.1.7
Summary: Sending emails and otp verifications is super simple with emailotp
Author: shaik afrid
Author-email: <afridayan01@gmail.com>
Keywords: email,emalilsending,emailotp,emailsending,emailsent,email-send,email-otp,email_otp,email_sending,email-sending,email-,email_,verification,email-verification,email_verification
Classifier: Intended Audience :: Developers
Classifier: Programming Language :: Python :: 3
Classifier: Operating System :: Unix
Classifier: Operating System :: MacOS :: MacOS X
Classifier: Operating System :: Microsoft :: Windows
License-File: LICENSE
Requires-Dist: requests
